distkv_ext/gpio/__init__.py
distkv_ext/gpio/client.py
distkv_ext/gpio/config.py
distkv_ext/gpio/model.py
distkv_ext/gpio/task.py
distkv_gpio-0.10.11.dist-info/METADATA
distkv_gpio-0.10.11.dist-info/WHEEL
distkv_gpio-0.10.11.dist-info/top_level.txt
distkv_gpio-0.10.11.dist-info/zip-safe
distkv_gpio-0.10.11.dist-info/RECORD
